topsis/__init__.py
topsis/topsis.py
topsis_trishti_102313056-1.0.0.dist-info/METADATA
topsis_trishti_102313056-1.0.0.dist-info/WHEEL
topsis_trishti_102313056-1.0.0.dist-info/entry_points.txt
topsis_trishti_102313056-1.0.0.dist-info/top_level.txt
topsis_trishti_102313056-1.0.0.dist-info/RECORD
