Metadata-Version: 2.4
Name: Topsis-Trishti-102313056
Version: 1.0.0
Summary: TOPSIS implementation
Author: Trishti
Author-email: trishti1110@gmail.com
Requires-Dist: pandas
Requires-Dist: numpy
Dynamic: author
Dynamic: author-email
Dynamic: requires-dist
Dynamic: summary
